.gitignore
LICENSE.txt
README.rst
setup.py
wxglvideo_demo_screenshot.png
motmot/__init__.py
motmot.wxglvideo.egg-info/.gitignore
motmot.wxglvideo.egg-info/PKG-INFO
motmot.wxglvideo.egg-info/SOURCES.txt
motmot.wxglvideo.egg-info/dependency_links.txt
motmot.wxglvideo.egg-info/entry_points.txt
motmot.wxglvideo.egg-info/namespace_packages.txt
motmot.wxglvideo.egg-info/stdeb.cfg
motmot.wxglvideo.egg-info/top_level.txt
motmot.wxglvideo.egg-info/zip-safe
motmot/wxglvideo/__init__.py
motmot/wxglvideo/demo.py
motmot/wxglvideo/demo.xrc
motmot/wxglvideo/demo_overlay.py
motmot/wxglvideo/simple_overlay.py
motmot/wxglvideo/wxglvideo.py
wx_test/README
wx_test/build.sh
wx_test/main.cpp
wx_test/main.h