Metadata-Version: 1.0
Name: motmot.wxglvideo
Version: 0.6.7
Summary: wx/OpenGL viewer of image sequences
Home-page: http://code.astraw.com/projects/motmot
Author: Andrew Straw
Author-email: strawman@astraw.com
License: BSD
Platform: UNKNOWN
